Metadata-Version: 2.1
Name: fdr-v4
Version: 0.1.0
Summary: Sample fdr lib
Author: Konstantinos Gyftodimos
Author-email: konstgyftodimos@gmail.com
Requires-Dist: aiohttp (==3.8.5)
Requires-Dist: aiohttp-retry (==2.8.3)
Requires-Dist: aiosignal (==1.3.1)
Requires-Dist: altgraph (==0.17.3)
Requires-Dist: amqp (==5.1.1)
Requires-Dist: antlr4-python3-runtime (==4.9.3)
Requires-Dist: appdirs (==1.4.4)
Requires-Dist: async-timeout (==4.0.3)
Requires-Dist: asyncssh (==2.13.2)
Requires-Dist: atpublic (==4.0)
Requires-Dist: attrs (==23.1.0)
Requires-Dist: bcrypt (==4.0.1)
Requires-Dist: billiard (==4.1.0)
Requires-Dist: bleach (==6.0.0)
Requires-Dist: cachetools (==5.3.1)
Requires-Dist: celery (==5.3.1)
Requires-Dist: certifi (==2023.7.22)
Requires-Dist: cffi (==1.15.1)
Requires-Dist: charset-normalizer (==3.2.0)
Requires-Dist: click (==8.1.7)
Requires-Dist: click-didyoumean (==0.3.0)
Requires-Dist: click-plugins (==1.1.1)
Requires-Dist: click-repl (==0.3.0)
Requires-Dist: colorama (==0.4.4)
Requires-Dist: commonmark (==0.9.1)
Requires-Dist: configobj (==5.0.8)
Requires-Dist: cryptography (==41.0.3)
Requires-Dist: cursor (==1.3.4)
Requires-Dist: dictdiffer (==0.9.0)
Requires-Dist: diskcache (==5.6.1)
Requires-Dist: distro (==1.8.0)
Requires-Dist: docutils (==0.20.1)
Requires-Dist: dpath (==2.1.6)
Requires-Dist: dulwich (==0.21.5)
Requires-Dist: dvc (==3.16.0)
Requires-Dist: dvc-data (==2.15.4)
Requires-Dist: dvc-gdrive (==2.20.0)
Requires-Dist: dvc-http (==2.30.2)
Requires-Dist: dvc-objects (==1.0.1)
Requires-Dist: dvc-render (==0.5.3)
Requires-Dist: dvc-ssh (==2.22.2)
Requires-Dist: dvc-studio-client (==0.13.0)
Requires-Dist: dvc-task (==0.3.0)
Requires-Dist: filelock (==3.12.2)
Requires-Dist: flatten-dict (==0.4.2)
Requires-Dist: flufl.lock (==7.1.1)
Requires-Dist: frozenlist (==1.4.0)
Requires-Dist: fsspec (==2023.6.0)
Requires-Dist: funcy (==2.0)
Requires-Dist: gitdb (==4.0.10)
Requires-Dist: GitPython (==3.1.32)
Requires-Dist: google-api-core (==2.11.1)
Requires-Dist: google-api-python-client (==2.97.0)
Requires-Dist: google-auth (==2.22.0)
Requires-Dist: google-auth-httplib2 (==0.1.0)
Requires-Dist: googleapis-common-protos (==1.60.0)
Requires-Dist: grandalf (==0.8)
Requires-Dist: httplib2 (==0.22.0)
Requires-Dist: hydra-core (==1.3.2)
Requires-Dist: idna (==3.4)
Requires-Dist: importlib-metadata (==6.8.0)
Requires-Dist: install (==1.3.5)
Requires-Dist: iterative-telemetry (==0.0.8)
Requires-Dist: jaraco.classes (==3.3.0)
Requires-Dist: keyboard (==0.13.5)
Requires-Dist: keyring (==24.2.0)
Requires-Dist: kombu (==5.3.1)
Requires-Dist: markdown-it-py (==3.0.0)
Requires-Dist: mdurl (==0.1.2)
Requires-Dist: more-itertools (==10.1.0)
Requires-Dist: multidict (==6.0.4)
Requires-Dist: networkx (==3.1)
Requires-Dist: numpy (==1.25.2)
Requires-Dist: oauth2client (==4.1.3)
Requires-Dist: omegaconf (==2.3.0)
Requires-Dist: orjson (==3.9.5)
Requires-Dist: packaging (==23.1)
Requires-Dist: pandas (==1.2.3)
Requires-Dist: pathspec (==0.11.2)
Requires-Dist: pefile (==2023.2.7)
Requires-Dist: Pillow (==10.0.0)
Requires-Dist: pkginfo (==1.9.6)
Requires-Dist: platformdirs (==3.10.0)
Requires-Dist: progressbar2 (==4.2.0)
Requires-Dist: prompt-toolkit (==3.0.39)
Requires-Dist: protobuf (==4.24.2)
Requires-Dist: psutil (==5.9.5)
Requires-Dist: pwinput (==1.0.3)
Requires-Dist: pyasn1 (==0.5.0)
Requires-Dist: pyasn1-modules (==0.3.0)
Requires-Dist: pychalk (==2.0.1)
Requires-Dist: pycparser (==2.21)
Requires-Dist: pydot (==1.4.2)
Requires-Dist: PyDrive2 (==1.17.0)
Requires-Dist: pygit2 (==1.12.2)
Requires-Dist: Pygments (==2.8.1)
Requires-Dist: pygtrie (==2.5.0)
Requires-Dist: pyinstaller (==5.13.0)
Requires-Dist: pyinstaller-hooks-contrib (==2023.5)
Requires-Dist: pynput (==1.7.6)
Requires-Dist: pyOpenSSL (==23.2.0)
Requires-Dist: pyparsing (==3.1.1)
Requires-Dist: python-dateutil (==2.8.2)
Requires-Dist: python-utils (==3.7.0)
Requires-Dist: pytz (==2023.3)
Requires-Dist: pywin32 (==306)
Requires-Dist: pywin32-ctypes (==0.2.2)
Requires-Dist: PyYAML (==6.0.1)
Requires-Dist: requests (==2.31.0)
Requires-Dist: requests-toolbelt (==1.0.0)
Requires-Dist: rfc3986 (==2.0.0)
Requires-Dist: rsa (==4.9)
Requires-Dist: ruamel.yaml (==0.17.32)
Requires-Dist: ruamel.yaml.clib (==0.2.7)
Requires-Dist: scmrepo (==1.3.1)
Requires-Dist: shortuuid (==1.0.11)
Requires-Dist: shtab (==1.6.4)
Requires-Dist: six (==1.15.0)
Requires-Dist: smmap (==5.0.0)
Requires-Dist: sqltrie (==0.7.0)
Requires-Dist: sshfs (==2023.7.0)
Requires-Dist: tabulate (==0.9.0)
Requires-Dist: termcolor (==2.3.0)
Requires-Dist: terminal-animation (==0.6)
Requires-Dist: tomlkit (==0.12.1)
Requires-Dist: tqdm (==4.65.0)
Requires-Dist: twine (==4.0.2)
Requires-Dist: typing-extensions (==4.7.1)
Requires-Dist: tzdata (==2023.3)
Requires-Dist: uritemplate (==4.1.1)
Requires-Dist: urllib3 (==1.26.16)
Requires-Dist: vine (==5.0.0)
Requires-Dist: voluptuous (==0.13.1)
Requires-Dist: wcwidth (==0.2.6)
Requires-Dist: webencodings (==0.5.1)
Requires-Dist: yarl (==1.9.2)
Requires-Dist: zc.lockfile (==3.0.post1)
Requires-Dist: zipp (==3.16.2)
